allfreqs/__init__.py
allfreqs/allfreqs.py
allfreqs/classes.py
allfreqs/cli.py
allfreqs/constants.py
allfreqs-0.3.0.dist-info/AUTHORS.rst
allfreqs-0.3.0.dist-info/LICENSE
allfreqs-0.3.0.dist-info/METADATA
allfreqs-0.3.0.dist-info/WHEEL
allfreqs-0.3.0.dist-info/entry_points.txt
allfreqs-0.3.0.dist-info/top_level.txt
allfreqs-0.3.0.dist-info/RECORD
