Metadata-Version: 2.1
Name: allfreqs
Version: 0.3.0
Summary: Calculate allele frequency from a sequence multialignment.
Home-page: https://github.com/robertopreste/allfreqs
Author: Roberto Preste
Author-email: robertopreste@gmail.com
License: MIT license
Keywords: allfreqs
Platform: UNKNOWN
Classifier: Development Status :: 2 - Pre-Alpha
Classifier: Intended Audience :: Developers
Classifier: License :: OSI Approved :: MIT License
Classifier: Natural Language :: English
Classifier: Programming Language :: Python :: 3
Classifier: Programming Language :: Python :: 3.6
Classifier: Programming Language :: Python :: 3.7
Requires-Dist: Click
Requires-Dist: scikit-bio
Requires-Dist: cached-property
